nomad_material_processing/__init__.py
nomad_material_processing/combinatorial.py
nomad_material_processing/crystal_growth.py
nomad_material_processing/epitaxy.py
nomad_material_processing/general.py
nomad_material_processing/utils.py
nomad_material_processing/solution/__init__.py
nomad_material_processing/solution/general.py
nomad_material_processing/solution/utils.py
nomad_material_processing/vapor_deposition/__init__.py
nomad_material_processing/vapor_deposition/general.py
nomad_material_processing/vapor_deposition/cvd/__init__.py
nomad_material_processing/vapor_deposition/cvd/general.py
nomad_material_processing/vapor_deposition/cvd/movpe.py
nomad_material_processing/vapor_deposition/pvd/__init__.py
nomad_material_processing/vapor_deposition/pvd/general.py
nomad_material_processing/vapor_deposition/pvd/mbe.py
nomad_material_processing/vapor_deposition/pvd/pld.py
nomad_material_processing/vapor_deposition/pvd/sputtering.py
nomad_material_processing/vapor_deposition/pvd/thermal.py
nomad_material_processing-1.0.5.dist-info/LICENSE
nomad_material_processing-1.0.5.dist-info/METADATA
nomad_material_processing-1.0.5.dist-info/WHEEL
nomad_material_processing-1.0.5.dist-info/entry_points.txt
nomad_material_processing-1.0.5.dist-info/top_level.txt
nomad_material_processing-1.0.5.dist-info/RECORD
