Metadata-Version: 2.2
Name: nomad-material-processing
Version: 1.0.5
Summary: A plugin for NOMAD containing base sections for material processing.
Author: Andrea Albino, Sebastian Brückner, Michael Götte, Ahmed Ilyas, Sarthak Kapoor, José A. Márquez, Hampus Näsström, Markus Scheidgen
Author-email: fairmat@physik.hu-berlin.de
Maintainer-email: FAIRmat <fairmat@physik.hu-berlin.de>
License:                                  Apache License
Project-URL: Homepage, https://github.com/FAIRmat-NFDI/nomad-material-processing
Project-URL: Bug Tracker, https://github.com/FAIRmat-NFDI/nomad-material-processing/issues
Classifier: Intended Audience :: Developers
Classifier: Operating System :: OS Independent
Classifier: Programming Language :: Python
Classifier: Programming Language :: Python :: 3.9
Classifier: Programming Language :: Python :: 3.10
Classifier: Programming Language :: Python :: 3.11
Classifier: Programming Language :: Python :: 3.12
Classifier: License :: OSI Approved :: Apache Software License
License-File: LICENSE
Requires-Dist: nomad-lab>=1.3.6
Provides-Extra: dev
Requires-Dist: pytest; extra == "dev"
Requires-Dist: ruff; extra == "dev"
Requires-Dist: structlog; extra == "dev"
